{
  "db_name": "SQLite",
  "query": "SELECT id, name, path, alias FROM media WHERE id = ?",
  "describe": {
    "columns": [
      {
        "name": "id",
        "ordinal": 0,
        "type_info": "Text"
      },
      {
        "name": "name",
        "ordinal": 1,
        "type_info": "Text"
      },
      {
        "name": "path",
        "ordinal": 2,
        "type_info": "Text"
      },
      {
        "name": "alias",
        "ordinal": 3,
        "type_info": "Text"
      }
    ],
    "parameters": {
      "Right": 1
    },
    "nullable": [
      false,
      false,
      false,
      true
    ]
  },
  "hash": "5a7163c99ae5befc75d9759810bed28f1669d4d2a4330e772762cb5c65ccef9f"
}
